cocktail_model_lib/__init__.py
cocktail_model_lib/base.py
cocktail_model_lib/functions.py
cocktail_model_lib/models.py
cocktail_model_lib/serializers.py
cocktail_model_lib-0.0.3.dist-info/METADATA
cocktail_model_lib-0.0.3.dist-info/WHEEL
cocktail_model_lib-0.0.3.dist-info/top_level.txt
cocktail_model_lib-0.0.3.dist-info/RECORD
